cloudMappingAI/__init__.py
cloudMappingAI/cloud_mapping_ai.py
cloudMappingAI/controlers/__init__.py
cloudMappingAI/controlers/create_dataset.py
cloudMappingAI/controlers/model.py
cloudMappingAI/controlers/preprosesing.py
cloudMappingAI/controlers/preprosesing_esrgan.py
cloudmappingai-0.0.2.dist-info/METADATA
cloudmappingai-0.0.2.dist-info/WHEEL
cloudmappingai-0.0.2.dist-info/licenses/LICENSE
cloudmappingai-0.0.2.dist-info/RECORD
