Metadata-Version: 2.4
Name: cloudMappingAI
Version: 0.0.2
Summary: Library for cloud mapping using Artificial Intelligence by semantic segmentation image
Author-email: Dzaky Faishalariq <mipamm4@gmail.com>
License-File: LICENSE
Classifier: License :: OSI Approved :: MIT License
Classifier: Operating System :: OS Independent
Classifier: Programming Language :: Python :: 3
Requires-Python: >=3.7
Requires-Dist: datasets==3.1.0
Requires-Dist: evaluate==0.4.3
Requires-Dist: roboflow==1.1.49
